{"task1_output": {"intent": {"name": "intro", "confidence": 0.7484842007687692}, "entities": [], "intent_ranking": [{"name": "intro", "confidence": 0.7484842007687692}, {"name": "ask_purpose", "confidence": 0.2515157992312311}], "text": "This is Mike from NTNT corporation"}, "task2_output": {"intent": {"name": "ask_purpose", "confidence": 0.7516487127982238}, "entities": [{"start": 24, "end": 31, "value": "prepaid", "entity": "connection", "confidence": 0.8309955001909003, "extractor": "CRFEntityExtractor"}], "intent_ranking": [{"name": "ask_purpose", "confidence": 0.7516487127982238}, {"name": "intro", "confidence": 0.24835128720177616}], "text": "you are being using our prepaid connection for couple of years now right"}, "task3_output": {"intent": {"name": "ask_purpose", "confidence": 0.7770288567583942}, "entities": [{"start": 21, "end": 29, "value": "postpaid", "entity": "connection", "confidence": 0.8310022072769346, "extractor": "CRFEntityExtractor"}], "intent_ranking": [{"name": "ask_purpose", "confidence": 0.7770288567583942}, {"name": "intro", "confidence": 0.22297114324160583}], "text": "How would you like a postpaid connection that allows you to make free unlimited voice calls with 3 8080 numbers"}}